{
  "event_id": "019e015c-e9ca-7783-a564-7f260fcb09b2",
  "occurred_at": "2026-05-07T07:35:26.922166Z",
  "type": "idx.knot_head",
  "data": {
    "blocked_from_state": null,
    "deferred_from_state": null,
    "gate": {
      "owner_kind": "agent"
    },
    "invariants": [],
    "knot_id": "thimble-b571",
    "next_step_metadata": {
      "action_kind": "produce",
      "action_state": "implementation",
      "output": {
        "artifact_type": "remote_main"
      },
      "owner": {
        "agent_model": null,
        "agent_name": null,
        "agent_version": null,
        "kind": "agent"
      }
    },
    "profile_id": "autopilot_no_planning",
    "state": "ready_for_implementation",
    "step_metadata": {
      "action_kind": "produce",
      "action_state": "implementation",
      "output": {
        "artifact_type": "remote_main"
      },
      "owner": {
        "agent_model": null,
        "agent_name": null,
        "agent_version": null,
        "kind": "agent"
      }
    },
    "terminal": false,
    "title": "Add status badges to README",
    "type": "work",
    "updated_at": "2026-05-07T07:35:26.922166Z",
    "workflow_id": "work_sdlc"
  }
}
