{
  "event_id": "019e016b-df4e-7402-8f4d-e97dfe90393b",
  "occurred_at": "2026-05-07T07:51:47.278985Z",
  "type": "idx.knot_head",
  "data": {
    "blocked_from_state": null,
    "deferred_from_state": null,
    "gate": {
      "owner_kind": "agent"
    },
    "invariants": [],
    "knot_id": "thimble-2c3a",
    "next_step_metadata": {
      "action_kind": "gate",
      "action_state": "implementation_review",
      "output": {
        "artifact_type": "remote_main"
      },
      "owner": {
        "agent_model": null,
        "agent_name": null,
        "agent_version": null,
        "kind": "agent"
      }
    },
    "profile_id": "autopilot",
    "state": "implementation",
    "step_metadata": {
      "action_kind": "produce",
      "action_state": "implementation",
      "output": {
        "artifact_type": "remote_main"
      },
      "owner": {
        "agent_model": null,
        "agent_name": null,
        "agent_version": null,
        "kind": "agent"
      }
    },
    "terminal": false,
    "title": "Replace SECURITY.md with vuln-reporting policy",
    "type": "work",
    "updated_at": "2026-05-07T07:51:47.278985Z",
    "workflow_id": "work_sdlc"
  },
  "precondition": {
    "profile_etag": "019e016b-df1a-76d3-b26e-ac1363c1296b"
  }
}
