{
  "event_id": "019e0185-8de3-7653-bf01-ef7009256fe7",
  "occurred_at": "2026-05-07T08:19:50.358197Z",
  "type": "idx.knot_head",
  "data": {
    "blocked_from_state": null,
    "deferred_from_state": null,
    "gate": {
      "owner_kind": "agent"
    },
    "invariants": [],
    "knot_id": "thimble-bdf7",
    "next_step_metadata": {
      "action_kind": "gate",
      "action_state": "implementation_review",
      "output": {
        "artifact_type": "remote_main"
      },
      "owner": {
        "agent_model": null,
        "agent_name": null,
        "agent_version": null,
        "kind": "agent"
      }
    },
    "profile_id": "autopilot_no_planning",
    "state": "implementation",
    "step_metadata": {
      "action_kind": "produce",
      "action_state": "implementation",
      "output": {
        "artifact_type": "remote_main"
      },
      "owner": {
        "agent_model": null,
        "agent_name": null,
        "agent_version": null,
        "kind": "agent"
      }
    },
    "terminal": false,
    "title": "PR CI: govulncheck",
    "type": "work",
    "updated_at": "2026-05-07T08:19:50.358197Z",
    "workflow_id": "work_sdlc"
  }
}
