{
  "event_id": "019e020f-d167-74d1-8fe8-1da147549c94",
  "occurred_at": "2026-05-07T10:50:51.623864Z",
  "type": "idx.knot_head",
  "data": {
    "blocked_from_state": null,
    "deferred_from_state": null,
    "gate": {
      "owner_kind": "agent"
    },
    "invariants": [],
    "knot_id": "thimble-bfd4",
    "profile_id": "lease",
    "state": "lease_terminated",
    "terminal": true,
    "title": "Lease: claim-thimble-a673",
    "type": "lease",
    "updated_at": "2026-05-07T10:50:51.623864Z",
    "workflow_id": "lease_sdlc"
  }
}
